{
    "UI_QuickFits_bind_open": "DaKai Quick Fits",
    "UI_QuickFits_title": "Quick Fits",
    "UI_QuickFits_inventory_button": "Quick Fits",
    "UI_QuickFits_context_open": "Quick Fits...",
    "UI_QuickFits_editor_editing_named": "BianJi: %1",
    "UI_QuickFits_editor_editing_new": "BianJi: Xin TaoZhuang",
    "UI_QuickFits_fallback_outfit_name": "TaoZhuang",
    "UI_QuickFits_debug_full_type": "fullType=%1",
    "UI_QuickFits_debug_body": "buwei=%1",
    "UI_QuickFits_debug_item_type": "itemType=%1",
    "UI_QuickFits_debug_included_false": "included=false",
    "UI_QuickFits_debug_ignored_true": "ignored=true",
    "UI_QuickFits_button_save": "BaoCun",
    "UI_QuickFits_button_capture_current": "SheWei DangQian ChuanDai",
    "UI_QuickFits_button_new": "XinJian",
    "UI_QuickFits_button_wear": "ChuanShang",
    "UI_QuickFits_button_add": "TianJia",
    "UI_QuickFits_button_take_off": "TuoXia",
    "UI_QuickFits_button_place_container": "FangRu RongQi",
    "UI_QuickFits_button_grab_all": "QuanBu NaQu",
    "UI_QuickFits_button_delete": "ShanChu",
    "UI_QuickFits_button_stop": "TingZhi",
    "UI_QuickFits_tooltip_wear": "Rang ni dangqian chuanzhe de zhuangbei yu ci taozhuang wanquan yizhi, bing xian xiaxia bu zai qi zhong de wu pin.",
    "UI_QuickFits_tooltip_add": "Ba ci taozhuang diejia dao ni yijing chuanzhe de zhuangbei shang, zhihui tihuan chongtu de buwei.",
    "UI_QuickFits_tooltip_take_off": "Zhishan chu ci taozhuang de chuanzai wu pin bing fang ru ni de beibao.",
    "UI_QuickFits_tooltip_place_container": "Ba taozhuang wu pin yidong dao rongqi zhong, youxian shiyong xuanzhong rongqi, ranhou shiyong zuijin de rongqi.",
    "UI_QuickFits_tooltip_grab_all": "Zai yi xuan huo fujin de wai bu rongqi zhong zhao dao taozhuang wu pin bing yi dong dao ni de beibao.",
    "UI_QuickFits_label_outfits": "TaoZhuang",
    "UI_QuickFits_label_items_in_outfit": "TaoZhuang WuPin",
    "UI_QuickFits_label_item_singular": "wu pin",
    "UI_QuickFits_label_item_plural": "wu pin",
    "UI_QuickFits_label_worn": "YI CHUAN",
    "UI_QuickFits_drop_hint_drag_here": "Jiang ke chuandai wu pin tuo dao zheli",
    "UI_QuickFits_drop_hint_capture": "huo shi yong BuHuo ChuanDai lai duqu ni dangqian de zhuangbei",
    "UI_QuickFits_drop_hint_release": "Song kai yi tianjia tuo dong de ke chuandai wu pin",
    "UI_QuickFits_debug_preview_language": "YuLan YuYan",
    "UI_QuickFits_progress_interrupted": "Yi ZhongDuan",
    "UI_QuickFits_progress_action_removing": "YiChu",
    "UI_QuickFits_progress_action_wearing": "ChuanDai",
    "UI_QuickFits_progress_action_moving": "YiDong",
    "UI_QuickFits_progress_status_count": "%1 (%2 / %3)",
    "UI_QuickFits_progress_status_with_item": "%1: %2 (%3 / %4)",
    "UI_QuickFits_progress_completed_phase": "Yi WanCheng: %1 (%2 / %3)",
    "UI_QuickFits_progress_interrupted_phase": "Yi ZhongDuan: %1 (%2 / %3)",
    "UI_QuickFits_result_apply_failed": "Quick Fits wu fa ying yong suo xuan tao zhuang.",
    "UI_QuickFits_result_action_apply": "yi yingyong.",
    "UI_QuickFits_result_action_remove": "yi tuoxia.",
    "UI_QuickFits_result_action_add": "yi tianjia.",
    "UI_QuickFits_result_action_wear": "yi jingque chuandai.",
    "UI_QuickFits_result_action_place": "yi fangru rongqi.",
    "UI_QuickFits_result_action_grab": "yi qudao beibao.",
    "UI_QuickFits_result_outfit_action": "%1 %2",
    "UI_QuickFits_result_equipped": "Yi chuandai %1 ge wu pin.",
    "UI_QuickFits_result_removed": "Yi yichu %1 ge wu pin.",
    "UI_QuickFits_result_blocked": "Bei yi chuan wu pin zu dang: %1.",
    "UI_QuickFits_result_moved": "Yi yidong %1 ge wu pin.",
    "UI_QuickFits_result_moved_target": "Yi jiang %1 ge wu pin yidong dao %2.",
    "UI_QuickFits_result_missing": "Que shao: %1.",
    "UI_QuickFits_draft_error_wearable_duplicates": "Zhi neng tianjia ke chuandai wu pin, tuo dong de chongfu xiang yi bei hulu.",
    "UI_QuickFits_draft_overlay_wearable_duplicates": "Zheli zhi ying fang ke chuandai wu pin. Chongfu xiang yi bei hulu.",
    "UI_QuickFits_draft_error_only_wearable": "Quick Fit zhi neng tianjia ke chuandai wu pin.",
    "UI_QuickFits_draft_overlay_only_wearable": "Zhi neng jiang ke chuandai wu pin fang ru tao zhuang.",
    "UI_QuickFits_draft_error_already_present": "Zhexie wu pin yi jing zai ci Quick Fit zhong.",
    "UI_QuickFits_draft_overlay_already_present": "Gai ke chuandai wu pin yi jing zai ci tao zhuang zhong.",
    "UI_QuickFits_draft_added": "Yi xiang cao gao zhong tianjia %1 ge ke chuandai wu pin.",
    "UI_QuickFits_draft_added_ignored": " Hu lue le %1 ge chongfu xiang he %2 ge bu ke chuandai wu pin.",
    "UI_QuickFits_status_selected_outfit": "Yi xuan tao zhuang: %1",
    "UI_QuickFits_status_captured_current": "Yi jiang wanjia dangqian chuanzai wu pin buhuo dao bianjiqi.",
    "UI_QuickFits_status_new_draft": "Yi chuangjian xin de kong tao zhuang cao gao. Tuo ru ke chuandai wu pin huo shi yong BuHuo ChuanDai.",
    "UI_QuickFits_status_saved_changes": "Yi bao cun tao zhuang genggai: %1",
    "UI_QuickFits_status_saved_new": "Yi bao cun tao zhuang: %1",
    "UI_QuickFits_status_select_before_delete": "Shanchu qian qing xian xuanze yi ge tao zhuang.",
    "UI_QuickFits_delete_confirm": "Shanchu %1?",
    "UI_QuickFits_status_deleted": "Yi shanchu suo xuan tao zhuang.",
    "UI_QuickFits_status_delete_failed": "Quick Fits wu fa shanchu suo xuan tao zhuang.",
    "UI_QuickFits_status_select_before_wear": "Chuandai qian qing xian xuanze yi ge tao zhuang.",
    "UI_QuickFits_status_select_before_add": "Tianjia qian qing xian xuanze yi ge tao zhuang.",
    "UI_QuickFits_status_select_before_place": "Fang ru rongqi qian qing xian xuanze yi ge tao zhuang.",
    "UI_QuickFits_status_select_before_grab": "Cong fujin rongqi quhui qian qing xian xuanze yi ge tao zhuang.",
    "UI_QuickFits_status_select_before_remove": "Tuo xia qian qing xian xuanze yi ge tao zhuang.",
    "UI_QuickFits_error_no_player": "Mei you ke yong wanjia.",
    "UI_QuickFits_error_select_outfit_first": "Qing xian xuanze yi ge tao zhuang.",
    "UI_QuickFits_error_no_container": "Mei you ke yong de yi xuan huo fujin rongqi gong Quick Fits shiyong.",
    "UI_QuickFits_error_no_external_container": "Mei you ke yong de yi xuan huo fujin wai bu rongqi gong Quick Fits shiyong.",
    "UI_QuickFits_error_save_empty": "Qing xuanze zhi shao yi ge yi chuan wu pin lai bao cun ci tao zhuang.",
    "UI_QuickFits_error_rename_missing": "Chongmingming tao zhuang qian qing xian shuru mingcheng.",
    "UI_QuickFits_default_outfit_name": "TaoZhuang %1",
    "UI_QuickFits_container_generic": "rongqi",
    "UI_QuickFits_container_inventory": "beibao",
    "UI_QuickFits_container_nearby": "fujin rongqi",
    "UI_QuickFits_context_item_wear": "ChuanShang",
    "UI_QuickFits_context_item_take_off": "TuoXia",
    "UI_QuickFits_context_item_grab": "Cong fujin naqu",
    "UI_QuickFits_context_item_place": "Fang dao fujin rongqi"
}